python_type.py
python_type-3.2.0.dist-info/METADATA
python_type-3.2.0.dist-info/WHEEL
python_type-3.2.0.dist-info/top_level.txt
python_type-3.2.0.dist-info/RECORD
