Metadata-Version: 2.4
Name: python-type
Version: 3.2.0
Summary: A powerful and flexible Python library for runtime type validation using type hints and custom type specifications. Available for Classes, Functions (lambda included), and Instances
Author-email: Daaviid8 <davidcortes1999@gmail.com>
License-Expression: MIT
Classifier: Programming Language :: Python :: 3
Classifier: Operating System :: OS Independent
Requires-Python: >=3.7
